genetic_optimizer/__init__.py
genetic_optimizer/Generator/__init__.py
genetic_optimizer/Generator/conf_exec.py
genetic_optimizer/Generator/generator.py
genetic_optimizer/src/DEFAULTS.ini
genetic_optimizer/src/STANDARDS.conf
genetic_optimizer/src/__init__.py
genetic_optimizer/src/conf_handler.py
genetic_optimizer/src/fitness.py
genetic_optimizer/src/meta.py
genetic_optimizer/src/optimizator.py
genetic_optimizer/src/pipeline.py
genetic_optimizer/src/preprocessing.py
genetic_optimizer/src/save.py
genetic_optimizer-0.1.8.dist-info/LICENSE
genetic_optimizer-0.1.8.dist-info/METADATA
genetic_optimizer-0.1.8.dist-info/WHEEL
genetic_optimizer-0.1.8.dist-info/top_level.txt
genetic_optimizer-0.1.8.dist-info/RECORD
