Metadata-Version: 2.1
Name: genetic-optimizer
Version: 0.1.8
Summary: Genetic algorithm optimizer using K-Means clustering with one way ANOVA algorithms.
Home-page: https://github.com/szachovy/GeneticOptimizer
Author: WJ Maj
Author-email: wjmaj98@gmail.com
License: MIT
Platform: UNKNOWN
Classifier: License :: OSI Approved :: MIT License
Classifier: Development Status :: 4 - Beta
Classifier: Intended Audience :: Science/Research
Classifier: Programming Language :: Python
Classifier: Programming Language :: Python :: 3
Classifier: Programming Language :: Python :: 3.6
Requires-Python: >=3.6.5
Requires-Dist: configparser (>=3.7.4)
Requires-Dist: numpy (>=1.16.3)
Requires-Dist: pandas (>=0.24.2)
Requires-Dist: xlsxwriter (>=1.1.8)
Requires-Dist: sklearn (>=0.0)
Requires-Dist: scipy (>=1.3.0)
Requires-Dist: matplotlib (>=3.1.0)
Requires-Dist: xlrd (>=1.0.0)
